q3as/__init__.py
q3as/api.py
q3as/client.py
q3as/run_options.py
q3as/algo/__init__.py
q3as/algo/optimizer.py
q3as/algo/types.py
q3as/algo/vqe.py
q3as/app/__init__.py
q3as/app/application.py
q3as/app/maxcut.py
q3as/app/qubo.py
q3as/encoding/__init__.py
q3as/encoding/app.py
q3as/encoding/numpy.py
q3as/encoding/optimizer.py
q3as/encoding/qiskit.py
q3as/encoding/quadratic.py
q3as/encoding/vqe.py
q3as/quadratic/__init__.py
q3as/quadratic/exceptions.py
q3as/quadratic/infinity.py
q3as/quadratic/converters/__init__.py
q3as/quadratic/converters/flip_problem_sense.py
q3as/quadratic/converters/inequality_to_equality.py
q3as/quadratic/converters/integer_to_binary.py
q3as/quadratic/converters/linear_equality_to_penalty.py
q3as/quadratic/converters/linear_inequality_to_penalty.py
q3as/quadratic/converters/quadratic_program_converter.py
q3as/quadratic/converters/quadratic_program_to_qubo.py
q3as/quadratic/problems/__init__.py
q3as/quadratic/problems/constraint.py
q3as/quadratic/problems/linear_constraint.py
q3as/quadratic/problems/linear_expression.py
q3as/quadratic/problems/quadratic_constraint.py
q3as/quadratic/problems/quadratic_expression.py
q3as/quadratic/problems/quadratic_objective.py
q3as/quadratic/problems/quadratic_program.py
q3as/quadratic/problems/quadratic_program_element.py
q3as/quadratic/problems/substitute_variables.py
q3as/quadratic/problems/types.py
q3as/quadratic/problems/variable.py
q3as/quadratic/translators/__init__.py
q3as/quadratic/translators/ising.py
q3as/quadratic/translators/prettyprint.py
q3as-0.1.4.dist-info/METADATA
q3as-0.1.4.dist-info/WHEEL
q3as-0.1.4.dist-info/licenses/NOTICE
q3as-0.1.4.dist-info/RECORD
